pigwig/__init__.py
pigwig/exceptions.py
pigwig/inotify.py
pigwig/multipart.py
pigwig/pigwig.py
pigwig/py.typed
pigwig/reloader_linux.py
pigwig/reloader_osx.py
pigwig/request_response.py
pigwig/routes.py
pigwig/templates_jinja.py
pigwig-0.8.4.dist-info/licenses/LICENSE
pigwig-0.8.4.dist-info/METADATA
pigwig-0.8.4.dist-info/WHEEL
pigwig-0.8.4.dist-info/top_level.txt
pigwig-0.8.4.dist-info/RECORD
