Metadata-Version: 2.4
Name: pigwig
Version: 0.8.4
Summary: a python 3.6+ WSGI framework
Author: raylu
Project-URL: homepage, https://github.com/raylu/pigwig
Project-URL: docs, https://pigwig.rtfd.org
Classifier: Programming Language :: Python :: 3.6
Classifier: Topic :: Internet :: WWW/HTTP :: WSGI
Requires-Python: >=3.6
License-File: LICENSE
Dynamic: license-file
